thinkPass/__init__.py
thinkPass/passwd.py
thinkPass/testing.py
thinkPass/data/names.csv
thinkPass/data/places.csv
thinkPass-2.0.0.1.dist-info/LICENSE.txt
thinkPass-2.0.0.1.dist-info/METADATA
thinkPass-2.0.0.1.dist-info/WHEEL
thinkPass-2.0.0.1.dist-info/top_level.txt
thinkPass-2.0.0.1.dist-info/RECORD
