Metadata-Version: 2.1
Name: thinkPass
Version: 2.0.0.1
Summary: password generator package
Author: Anant Chaudhary
Classifier: Programming Language :: Python :: 3
Classifier: License :: OSI Approved :: MIT License
Classifier: Operating System :: OS Independent
Requires-Python: >=3.6
License-File: LICENSE.txt
